Topsis_102053042/Topsis_102053042.py
Topsis_102053042/__init__.py
Topsis_Aryan_102053042-0.0.1.dist-info/LICENCE.txt
Topsis_Aryan_102053042-0.0.1.dist-info/METADATA
Topsis_Aryan_102053042-0.0.1.dist-info/WHEEL
Topsis_Aryan_102053042-0.0.1.dist-info/top_level.txt
Topsis_Aryan_102053042-0.0.1.dist-info/RECORD
