Metadata-Version: 2.1
Name: Topsis-Aryan-102053042
Version: 0.0.1
Summary: A package to Implement Topsis Model
Home-page: 
Author: Aryan Sood
Author-email: asood2_be20@thapar.edu
License: MIT
Keywords: TOPSIS
Classifier: Development Status :: 5 - Production/Stable
Classifier: Intended Audience :: Education
Classifier: Operating System :: Microsoft :: Windows :: Windows 11
Classifier: License :: OSI Approved :: MIT License
Classifier: Programming Language :: Python :: 3
License-File: LICENCE.txt
